skillhub_mcp/__init__.py
skillhub_mcp/__main__.py
skillhub_mcp/_server.py
skillhub_mcp/_version.py
skillhub_mcp-1.0.5.dist-info/WHEEL
skillhub_mcp-1.0.5.dist-info/entry_points.txt
skillhub_mcp-1.0.5.dist-info/METADATA
skillhub_mcp-1.0.5.dist-info/RECORD
