Metadata-Version: 2.3
Name: skillhub-mcp
Version: 1.0.5
Summary: MCP server that exposes Claude-style skills to any MCP client.
Keywords: mcp,skills,fastmcp,claude
Author: Eleanor Berger
Author-email: Eleanor Berger <eleanor@214140846.net>
License: MIT License
Classifier: Development Status :: 3 - Alpha
Classifier: Intended Audience :: Developers
Classifier: License :: OSI Approved :: MIT License
Classifier: Programming Language :: Python
Classifier: Programming Language :: Python :: 3
Classifier: Programming Language :: Python :: 3.12
Requires-Dist: fastmcp>=2.2.5
Requires-Dist: pyyaml>=6.0
Requires-Python: >=3.12
Project-URL: Homepage, https://github.com/214140846/skillhub-mcp
Project-URL: Issues, https://github.com/214140846/skillhub-mcp/issues
